LICENSE
MANIFEST.in
README.md
setup.py
koi/__init__.py
koi.egg-info/PKG-INFO
koi.egg-info/SOURCES.txt
koi.egg-info/dependency_links.txt
koi.egg-info/requires.txt
koi.egg-info/top_level.txt
koi/core/__init__.py
koi/core/client.py
koi/ecs/__init__.py
koi/ecs/ecsclient.py