Metadata-Version: 1.1
Name: koi
Version: 0.1.8
Summary: 3rd-party Aliyun python client which supports python3
Home-page: https://github.com/observerss/koi
Author: Jingchao Hu(observerss)
Author-email: jingchaohu@gmail.com
License: The MIT License (MIT)
